mause_rpc/__init__.py
mause_rpc/client.py
mause_rpc/py.typed
mause_rpc/server.py
mause_rpc-0.0.21.dist-info/LICENSE
mause_rpc-0.0.21.dist-info/METADATA
mause_rpc-0.0.21.dist-info/WHEEL
mause_rpc-0.0.21.dist-info/RECORD
