Metadata-Version: 2.1
Name: mause_rpc
Version: 0.0.21
Summary: A dumb as hell rpc implementation built on rabbitmq
Home-page: https://github.com/Mause/rpc
License: MIT
Keywords: rabbitmq,rpc
Author: Elliana May
Author-email: me@mause.me
Requires-Python: >=3.8.1,<4.0.0
Classifier: Development Status :: 3 - Alpha
Classifier: Intended Audience :: Developers
Classifier: License :: OSI Approved :: MIT License
Classifier: Programming Language :: Python :: 3
Classifier: Programming Language :: Python :: 3.9
Classifier: Programming Language :: Python :: 3.10
Classifier: Programming Language :: Python :: 3.11
Classifier: Programming Language :: Python :: 3.12
Classifier: Topic :: Software Development :: Libraries :: Python Modules
Classifier: Typing :: Typed
Requires-Dist: dill (>=0.3.1,<0.4.0)
Requires-Dist: pika (>=1.1.0,<2.0.0)
Requires-Dist: retry (>=0.9.2,<0.10.0)
Project-URL: Repository, https://github.com/Mause/rpc
